[
  {
    "id": "6",
    "headline": "Snazzy Wallpapers",
    "summary": "Awesome site for snazzy techno wallpapers.",
    "date": "20000718214128",
    "link": "chapter3.net",
    "local_path": "net_interest/saved_webpages/link_6/index.html",
    "images": 0,
    "size": 1364
  },
  {
    "id": "10",
    "headline": "DVD Price Search",
    "summary": "DVD Price Search is excellent.  Check out it's search engine to find the lowest DVD price.  It's also a great source for coupons that can be used on DVDs and on other items (books, electronics, etc)",
    "date": "20000720114349",
    "link": "www.dvdpricesearch.net",
    "local_path": "net_interest/saved_webpages/link_10/index.html",
    "images": 10,
    "size": 74443
  },
  {
    "id": "11",
    "headline": "More Snazzy Wallpapers",
    "summary": "deeper linked into Chapter3.....\nautomatic for the people.\n",
    "date": "20000720142027",
    "link": "chapter3.net/imperium/index.html",
    "local_path": "net_interest/saved_webpages/link_11/index.html",
    "images": 0,
    "size": 1364
  },
  {
    "id": "28",
    "headline": "Ightetto.com - Ebonics, Movies, and More!",
    "summary": "",
    "date": "20000831080904",
    "link": "www.ighetto.com",
    "local_path": "net_interest/saved_webpages/link_28/index.html",
    "images": 0,
    "size": 9592
  },
  {
    "id": "29",
    "headline": "Sinfest the Comic Strip",
    "summary": "Sinfest is an awesome comic strip that is like a mix of Calvin & Hobbes with the Sassyness of Penny Arcade.  you must read it now. (refered to me by Rex, yeah rex!)",
    "date": "20000903185244",
    "link": "www.sinfest.net",
    "local_path": "net_interest/saved_webpages/link_29/index.html",
    "images": 5,
    "size": 13316
  },
  {
    "id": "39",
    "headline": "Olympic athletes get ambitious condom allowance",
    "summary": "That's a lot of condoms.",
    "date": "20000909134424",
    "link": "dailynews.yahoo.com/h/nm/20000908/hl/condoms.html",
    "local_path": "net_interest/saved_webpages/link_39/index.html",
    "images": 10,
    "size": 778190
  },
  {
    "id": "81",
    "headline": "Shroom's Cool Site",
    "summary": "",
    "date": "20001009152003",
    "link": "shroom.dv8.org",
    "local_path": "net_interest/saved_webpages/link_81/index.html",
    "images": 0,
    "size": 11391
  },
  {
    "id": "110",
    "headline": "Hunter S. Thompson Article on ESPN.com",
    "summary": "Baseball has become unruly\nBy Hunter S. Thompson\nSpecial to Page 2\n\nHi, folks. My name is Thompson, and I don't have much space for this high-speed presentation, so let's get started and see how tight we can make it. My job is to devise a whole new se",
    "date": "20001106152625",
    "link": "espn.go.com/page2/s/thompson/001106.html",
    "local_path": "net_interest/saved_webpages/link_110/index.html",
    "images": 0,
    "size": 345
  },
  {
    "id": "113",
    "headline": "Driveways of the Rich and Famous",
    "summary": "",
    "date": "20001108180910",
    "link": "www.driveways.com/",
    "local_path": "net_interest/saved_webpages/link_113/index.html",
    "images": 0,
    "size": 8373
  },
  {
    "id": "115",
    "headline": "Am I hot or Not",
    "summary": "fun game to play.\ninteresting combo of insulting people and voyeristic porn.\n",
    "date": "20001113180159",
    "link": "www.amihotornot.com/",
    "local_path": "net_interest/saved_webpages/link_115/index.html",
    "images": 0,
    "size": 203877
  },
  {
    "id": "123",
    "headline": "Inside Tech Support Hell",
    "summary": "",
    "date": "20001206163910",
    "link": "www.eastbayexpress.com/archive/120100/cover_120100.html",
    "local_path": "net_interest/saved_webpages/link_123/index.html",
    "images": 7,
    "size": 497016
  },
  {
    "id": "171",
    "headline": "Hunter gets pissed about the handleing of his new film!",
    "summary": "",
    "date": "20010224130208",
    "link": "www.aintitcoolnews.com/display.cgi?id=8218",
    "local_path": "net_interest/saved_webpages/link_171/index.html",
    "images": 4,
    "size": 16736
  },
  {
    "id": "172",
    "headline": "Berkely Breathed Interview",
    "summary": "",
    "date": "20010224130251",
    "link": "slashdot.org/article.pl?sid=01/02/19/1456220",
    "local_path": "net_interest/saved_webpages/link_172/index.html",
    "images": 5,
    "size": 296356
  },
  {
    "id": "176",
    "headline": "The Drug Tunnel",
    "summary": "",
    "date": "20010228125035",
    "link": "http://dailynews.yahoo.com/h/ap/20010227/us/drug_tunnel.html",
    "local_path": "net_interest/saved_webpages/link_176/index.html",
    "images": 10,
    "size": 778198
  },
  {
    "id": "181",
    "headline": "All your base are belong to us",
    "summary": "",
    "date": "20010303123712",
    "link": "http://www.theregister.co.uk/content/28/17122.html",
    "local_path": "net_interest/saved_webpages/link_181/index.html",
    "images": 0,
    "size": 54084
  },
  {
    "id": "187",
    "headline": "Singer - Songwriter - Hooker",
    "summary": "",
    "date": "20010309102803",
    "link": "http://www.michaelarenee.com",
    "local_path": "net_interest/saved_webpages/link_187/index.html",
    "images": 10,
    "size": 415568
  },
  {
    "id": "190",
    "headline": "From now on this is THE place to find out if a movie is good.",
    "summary": "",
    "date": "20010312175913",
    "link": "http://www.capalert.com/capreports/#Media",
    "local_path": "net_interest/saved_webpages/link_190/index.html",
    "images": 6,
    "size": 289721
  },
  {
    "id": "196",
    "headline": "Green Plastic - A Site about Radiohead",
    "summary": "",
    "date": "20010321131411",
    "link": "http://www.greenplastic.com",
    "local_path": "net_interest/saved_webpages/link_196/index.html",
    "images": 1,
    "size": 33661
  },
  {
    "id": "212",
    "headline": "Odyssey probe blasts off for Mars",
    "summary": "",
    "date": "20010408101428",
    "link": "http://www.cnn.com/2001/TECH/space/04/07/mars.odyssey/index.html",
    "local_path": "net_interest/saved_webpages/link_212/index.html",
    "images": 10,
    "size": 23022
  },
  {
    "id": "214",
    "headline": "Shakespeare Insult Generator",
    "summary": "",
    "date": "20010408111744",
    "link": "http://www.pangloss.com/seidel/Shaker/index.html?",
    "local_path": "net_interest/saved_webpages/link_214/index.html",
    "images": 1,
    "size": 1050
  },
  {
    "id": "217",
    "headline": "Steven Bushemi stabbed in the face",
    "summary": "",
    "date": "20010416155509",
    "link": "http://dailynews.yahoo.com/h/nm/20010414/en/people-buscemi_1.html",
    "local_path": "net_interest/saved_webpages/link_217/index.html",
    "images": 10,
    "size": 778800
  },
  {
    "id": "228",
    "headline": "Lore: I  think",
    "summary": "",
    "date": "20010421111130",
    "link": "http://brunching.com/features/loreithink.html",
    "local_path": "net_interest/saved_webpages/link_228/index.html",
    "images": 0,
    "size": 0
  },
  {
    "id": "236",
    "headline": "A new secret Quentin Tarantino film?",
    "summary": "",
    "date": "20010504090006",
    "link": "http://www.aintitcool.com/display.cgi?id=8893",
    "local_path": "net_interest/saved_webpages/link_236/index.html",
    "images": 3,
    "size": 24893
  },
  {
    "id": "239",
    "headline": "SMC: Summer Movie Prediction",
    "summary": "",
    "date": "20010505115412",
    "link": "http://brunching.com/selfmade/summermovies2001.html",
    "local_path": "net_interest/saved_webpages/link_239/index.html",
    "images": 0,
    "size": 0
  },
  {
    "id": "245",
    "headline": "BoobScan",
    "summary": "",
    "date": "20010513101748",
    "link": "http://www.boobscan.com",
    "local_path": "net_interest/saved_webpages/link_245/index.html",
    "images": 0,
    "size": 44170
  },
  {
    "id": "250",
    "headline": "R.E.M. Stay Dry in Toronto",
    "summary": "",
    "date": "20010520115842",
    "link": "http://www.rollingstone.com/news/newsarticle.asp?nid=13918",
    "local_path": "net_interest/saved_webpages/link_250/index.html",
    "images": 10,
    "size": 521175
  },
  {
    "id": "258",
    "headline": "No Sneeze Cloned Cats",
    "summary": "",
    "date": "20010627225059",
    "link": "http://dailynews.yahoo.com/h/nm/20010627/sc/health_cats_dc_2.html",
    "local_path": "net_interest/saved_webpages/link_258/index.html",
    "images": 10,
    "size": 778800
  },
  {
    "id": "260",
    "headline": "Citizen Kane on DVD!!!",
    "summary": "",
    "date": "20010629070426",
    "link": "http://dailynews.yahoo.com/h/nm/20010629/en/film-kane_1.html",
    "local_path": "net_interest/saved_webpages/link_260/index.html",
    "images": 10,
    "size": 778800
  },
  {
    "id": "268",
    "headline": "Funny Comic about Episode II",
    "summary": "",
    "date": "20010808110510",
    "link": "http://www.whenigrowup.net/d/20010807.html",
    "local_path": "net_interest/saved_webpages/link_268/index.html",
    "images": 0,
    "size": 0
  },
  {
    "id": "270",
    "headline": "./ - Burning a NeXT Cube",
    "summary": "",
    "date": "20010811200245",
    "link": "http://simson.net/photos/hacks/cubefire.html",
    "local_path": "net_interest/saved_webpages/link_270/index.html",
    "images": 1,
    "size": 120671
  },
  {
    "id": "286",
    "headline": "Mobile Phones May Do Harm by Speeding Up Brain",
    "summary": "",
    "date": "20010922042103",
    "link": "http://dailynews.yahoo.com/htx/nm/20010921/tc/health_mobile_dc_2.html",
    "local_path": "net_interest/saved_webpages/link_286/index.html",
    "images": 10,
    "size": 778800
  },
  {
    "id": "289",
    "headline": "StratFor: U.S. Must Create Theaters of Operations",
    "summary": "",
    "date": "20010924175948",
    "link": "http://www.stratfor.com/home/0109242145.htm",
    "local_path": "net_interest/saved_webpages/link_289/index.html",
    "images": 10,
    "size": 706016
  },
  {
    "id": "290",
    "headline": "Thinking the unthinkable: A takeover of Disney",
    "summary": "",
    "date": "20010926142105",
    "link": "http://biz.yahoo.com/rf/010926/n26178657_1.html",
    "local_path": "net_interest/saved_webpages/link_290/index.html",
    "images": 10,
    "size": 2612571
  },
  {
    "id": "293",
    "headline": "S.Africa to Launch Massive Elephant Relocation",
    "summary": "",
    "date": "20011002231933",
    "link": "http://dailynews.yahoo.com/h/nm/20011002/sc/environment_africa_elephants_dc_2.html",
    "local_path": "net_interest/saved_webpages/link_293/index.html",
    "images": 10,
    "size": 778800
  }
]